bal/__init__.py
bal/context.py
bal/context_ioc.py
bal/data_model.py
bal/data_object.py
bal/analyzers/__init__.py
bal/analyzers/visualizer_analyzer.py
bal-0.1.dist-info/METADATA
bal-0.1.dist-info/WHEEL
bal-0.1.dist-info/top_level.txt
bal-0.1.dist-info/RECORD
