Metadata-Version: 2.1
Name: bal
Version: 0.1
Summary: A framework for analyzing and manipulating binary data
Home-page: UNKNOWN
Author: Red Balloon Security
Author-email: quack-tech@redballoonsecurity.com
License: UNKNOWN
Platform: UNKNOWN
Requires-Dist: six
Requires-Dist: enum34 ; python_version < "3.4"
Requires-Dist: typing ; python_version < "3.5"
Provides-Extra: docs
Requires-Dist: sphinx ; extra == 'docs'
Requires-Dist: sphinx-rtd-theme ; extra == 'docs'
Requires-Dist: m2r ; extra == 'docs'
Provides-Extra: examples
Requires-Dist: wget ; extra == 'examples'
